typora_git_uploader/__init__.py
typora_git_uploader/main.py
typora_upload_util-1.0.2.dist-info/LICENSE
typora_upload_util-1.0.2.dist-info/METADATA
typora_upload_util-1.0.2.dist-info/WHEEL
typora_upload_util-1.0.2.dist-info/entry_points.txt
typora_upload_util-1.0.2.dist-info/top_level.txt
typora_upload_util-1.0.2.dist-info/RECORD
